Metadata-Version: 2.0
Name: odoo8-addon-account-payment-partner
Version: 8.0.0.2.0.99.dev27
Summary: Adds payment mode on partners and invoices
Home-page: https://github.com/OCA/bank-payment
Author: Akretion, Serv. Tecnol. Avanzados - Pedro M. Baeza, Odoo Community Association (OCA)
Author-email: support@odoo-community.org
License: AGPL-3
Platform: UNKNOWN
Classifier: Programming Language :: Python
Classifier: Framework :: Odoo
Classifier: License :: OSI Approved :: GNU Affero General Public License v3
Requires-Python: ~=2.7
Requires-Dist: odoo (<9.0a,>=8.0a)
Requires-Dist: odoo8-addon-account-banking-payment-export
